mpan/__init__.py
mpan/common.py
mpan/data.py
mpan/distributor.py
mpan/exceptions.py
mpan/generation/faker.py
mpan/generation/helpers.py
mpan/generation/mimesis.py
mpan/helpers.py
mpan/meter_time_switch_code.py
mpan/mpan.py
mpan/profile_class.py
mpan-2.1.0.dist-info/LICENSE
mpan-2.1.0.dist-info/WHEEL
mpan-2.1.0.dist-info/METADATA
mpan-2.1.0.dist-info/RECORD
